campus_cli/__init__.py
campus_cli/cli.py
campus_cli-0.2.2.dist-info/METADATA
campus_cli-0.2.2.dist-info/WHEEL
campus_cli-0.2.2.dist-info/entry_points.txt
campus_cli-0.2.2.dist-info/RECORD
