Metadata-Version: 2.1
Name: campus-cli
Version: 0.2.2
Summary: 
Author: gazaboo
Author-email: florian.dadouchi@gmail.com
Requires-Python: >=3.11,<4.0
Classifier: Programming Language :: Python :: 3
Classifier: Programming Language :: Python :: 3.11
Classifier: Programming Language :: Python :: 3.12
Requires-Dist: click (>=8.1.7,<9.0.0)
Requires-Dist: click-completion (>=0.5.2,<0.6.0)
Requires-Dist: nbformat (>=5.10.4,<6.0.0)
Requires-Dist: requests (>=2.32.3,<3.0.0)
Requires-Dist: textract (>=1.6.5,<2.0.0)
